{
	"backtraceGraph" : 
	{
		"commands" : 
		[
			"install"
		],
		"files" : 
		[
			"/home/w88/code/esp-idf/components/mbedtls/mbedtls/tf-psa-crypto/core/CMakeLists.txt"
		],
		"nodes" : 
		[
			{
				"file" : 0
			},
			{
				"command" : 0,
				"file" : 0,
				"line" : 186,
				"parent" : 0
			},
			{
				"command" : 0,
				"file" : 0,
				"line" : 193,
				"parent" : 0
			}
		]
	},
	"codemodelVersion" : 
	{
		"major" : 2,
		"minor" : 10
	},
	"installers" : 
	[
		{
			"backtrace" : 1,
			"component" : "Unspecified",
			"destination" : "lib",
			"paths" : 
			[
				"esp-idf/mbedtls/mbedtls/tf-psa-crypto/core/libtfpsacrypto.a"
			],
			"targetId" : "tfpsacrypto::@a178143d93fb03652d8f",
			"targetIndex" : 152,
			"type" : "target"
		},
		{
			"backtrace" : 2,
			"component" : "Unspecified",
			"destination" : "lib",
			"paths" : 
			[
				"esp-idf/mbedtls/mbedtls/tf-psa-crypto/core/libtfpsacrypto.a"
			],
			"targetId" : "tfpsacrypto::@a178143d93fb03652d8f",
			"targetIndex" : 152,
			"type" : "target"
		}
	],
	"paths" : 
	{
		"build" : "esp-idf/mbedtls/mbedtls/tf-psa-crypto/core",
		"source" : "/home/w88/code/esp-idf/components/mbedtls/mbedtls/tf-psa-crypto/core"
	}
}
